memformer/__init__.py
memformer/autoregressive_wrapper.py
memformer/memformer.py
memformer/mrbp.py
memformer-0.3.1.dist-info/LICENSE
memformer-0.3.1.dist-info/METADATA
memformer-0.3.1.dist-info/WHEEL
memformer-0.3.1.dist-info/top_level.txt
memformer-0.3.1.dist-info/RECORD
